Workbook

Sheet 📊 Dashboard
B1: 💑 COUPLE GOALS TRACKER | 2025 – 2026
B2: Track. Achieve. Celebrate. — Your joint goal-setting platform
B3: 🧑 HIS GOALS | C3: 👩 HER GOALS | D3: 💑 COUPLE GOALS | E3: ✅ TOTAL ACHIEVED | F3: 🔥 STREAK (Days) | G3: 📅 Last Updated
B4: =COUNTA('🧑 His Goals'!B5:B54) -> 50 | C4: =COUNTA('👩 Her Goals'!B5:B54) -> 50 | D4: =COUNTA('💑 Our Goals'!B5:B54) -> 50 | E4: =COUNTIF('🏆 Achieved'!D2:D200,"Achieved") -> 0 | F4: 30 | G4: =TODAY() -> 46080
B6: 📈 GOAL PROGRESS OVERVIEW
B7: # | C7: Goal Name | D7: Category | E7: Owner | F7: Target Date | G7: Progress % | H7: Status | I7: Priority
B8: 1 | C8: Buy our first home together | D8: Finance | E8: Couple | F8: Dec 2025 | G8: 0.35 | H8: In Progress | I8: High
B9: 2 | C9: Travel to 3 new countries | D9: Travel | E9: Couple | F9: Dec 2026 | G9: 0.33 | H9: In Progress | I9: High
B10: 3 | C10: Run a 5K together | D10: Health | E10: Couple | F10: Jun 2025 | G10: 0.6 | H10: In Progress | I10: Medium
B11: 4 | C11: Save Emergency Fund (6 months) | D11: Finance | E11: Him | F11: Sep 2025 | G11: 0.5 | H11: In Progress | I11: High
B12: 5 | C12: Get promoted / Grow income 20% | D12: Career | E12: Him | F12: Dec 2025 | G12: 0.4 | H12: In Progress | I12: High
B13: 6 | C13: Read 24 books this year | D13: Personal Growth | E13: Her | F13: Dec 2025 | G13: 0.58 | H13: In Progress | I13: Medium
B14: 7 | C14: Launch side business | D14: Finance | E14: Her | F14: Mar 2026 | G14: 0.2 | H14: In Progress | I14: High
B15: 8 | C15: Monthly date nights (12) | D15: Relationship | E15: Couple | F15: Dec 2025 | G15: 0.75 | H15: In Progress | I15: Medium
B16: 9 | C16: Learn new language (A2) | D16: Personal Growth | E16: Him | F16: Jun 2026 | G16: 0.3 | H16: In Progress | I16: Low
B17: 10 | C17: Improve mental wellness routine | D17: Health | E17: Her | F17: Ongoing | G17: 0.65 | H17: In Progress | I17: Medium
B20: 📊 ANALYTICS SUMMARY
B21: Metric | C21: Him | D21: Her | E21: Couple | F21: Total
B22: Goals Set | C22: =COUNTA('🧑 His Goals'!B5:B54) -> 50 | D22: =COUNTA('👩 Her Goals'!B5:B54) -> 50 | E22: =COUNTA('💑 Our Goals'!B5:B54) -> 50 | F22: =C22+D22+E22 -> 150
B23: Goals Achieved | C23: =COUNTIFS('🏆 Achieved'!C2:C100,"Him",'🏆 Achieved'!D2:D100,"Achieved") -> 0 | D23: =COUNTIFS('🏆 Achieved'!C2:C100,"Her",'🏆 Achieved'!D2:D100,"Achieved") -> 0 | E23: =COUNTIFS('🏆 Achieved'!C2:C100,"Couple",'🏆 Achieved'!D2:D100,"Achieved") -> 0 | F23: =COUNTIF('🏆 Achieved'!D2:D100,"Achieved") -> 0
B24: In Progress | C24: 2 | D24: 3 | E24: 3 | F24: =C23+D23+E23 -> 0
B25: Avg Progress % | C25: 40% | D25: 46% | E25: 54%
B26: High Priority | C26: 2 | D26: 2 | E26: 2
B28: 💡 Tip: Update progress in each individual sheet. This dashboard auto-updates! | Review goals monthly together.

Sheet 🧑 His Goals
B1: 🧑 HIM'S GOALS | Personal Goal Planner
B2: Set ambitious goals. Track relentlessly. Celebrate every win.
C3: Total Goals | D3: Completed | E3: In Progress | F3: Completion Rate
C4: =COUNTA(C5:C54) -> 7 | D4: =COUNTIF(H5:H54,"Completed") -> 0 | E4: =COUNTIF(H5:H54,"In Progress") -> 0 | F4: =IFERROR(COUNTIF(H5:H54,"Completed")/COUNTA(H5:H54),0) -> 0
B5: 📋 GOAL LIST — HIM | Add, update, and track your goals below
B6: # | C6: Goal Title | D6: Category | E6: Target Date | F6: Progress % | G6: Measure / KPI | H6: Priority | I6: Status | J6: Notes
B7: 1 | C7: Save Emergency Fund (6 months income) | D7: Finance | E7: Sep 2025 | F7: 0.5 | G7: Savings balance = $X | H7: High | I7: In Progress | J7: Track in savings account monthly
B8: 2 | C8: Get promoted / Grow income 20% | D8: Career | E8: Dec 2025 | F8: 0.4 | G8: Salary / income increase | H8: High | I8: In Progress
B9: 3 | C9: Work out 4x per week | D9: Health | E9: Ongoing | F9: 0.6 | G9: Workouts logged per week | H9: High | I9: In Progress | J9: Use gym app to track
B10: 4 | C10: Learn new language (A2 level) | D10: Personal Growth | E10: Jun 2026 | F10: 0.3 | G10: Duolingo streak + A2 test | H10: Low | I10: In Progress
B11: 5 | C11: Read 12 books | D11: Personal Growth | E11: Dec 2025 | F11: 0.42 | G11: Books read this year | H11: Medium | I11: In Progress
B12: 6 | C12: Invest 20% of income monthly | D12: Finance | E12: Ongoing | F12: 0.55 | G12: % of income invested | H12: High | I12: In Progress
B13: 7
B14: 8
B15: 9
B16: 10
B17: 11
B18: 12
B19: 13
B20: 14
B21: 15
B22: 16
B23: 17
B24: 18
... B56: 50
B58: 💡 Tip: Review and update progress weekly. Use the Status dropdown to mark goals Completed, then log them in the 🏆 Achieved tab!

Sheet 👩 Her Goals
B1: 👩 HER'S GOALS | Personal Goal Planner
B2: Set ambitious goals. Track relentlessly. Celebrate every win.
C3: Total Goals | D3: Completed | E3: In Progress | F3: Completion Rate
C4: =COUNTA(C7:C54) -> 6 | D4: =COUNTIF(H5:H54,"Completed") -> 0 | E4: =COUNTIF(H5:H54,"In Progress") -> 0 | F4: =IFERROR(COUNTIF(H5:H54,"Completed")/COUNTA(H5:H54),0) -> 0
B5: 📋 GOAL LIST — HER | Add, update, and track your goals below
B6: # | C6: Goal Title | D6: Category | E6: Target Date | F6: Progress % | G6: Measure / KPI | H6: Priority | I6: Status | J6: Notes
B7: 1 | C7: Launch side business | D7: Finance | E7: Mar 2026 | F7: 0.2 | G7: Business launched & 1st sale | H7: High | I7: In Progress
B8: 2 | C8: Read 24 books this year | D8: Personal Growth | E8: Dec 2025 | F8: 0.58 | G8: Books completed | H8: Medium | I8: In Progress
B9: 3 | C9: Improve mental wellness routine | D9: Health | E9: Ongoing | F9: 0.65 | G9: Daily habit streak | H9: Medium | I9: In Progress | J9: Journaling + meditation
B10: 4 | C10: Run 5K under 30 mins | D10: Health | E10: Jun 2025 | F10: 0.5 | G10: 5K race time | H10: Medium | I10: In Progress
B11: 5 | C11: Build professional network (+50 connections) | D11: Career | E11: Dec 2025 | F11: 0.4 | G11: New meaningful connections | H11: High | I11: In Progress
B12: 6 | C12: Take a solo trip | D12: Travel | E12: Dec 2026 | F12: 0.1 | G12: Trip booked and completed | H12: Medium | I12: Not Started
B13: 7
B14: 8
B15: 9
B16: 10
B17: 11
B18: 12
B19: 13
B20: 14
B21: 15
B22: 16
B23: 17
B24: 18
... B56: 50
B58: 💡 Tip: Review and update progress weekly. Use the Status dropdown to mark goals Completed, then log them in the 🏆 Achieved tab!

Sheet 💑 Our Goals
B1: 💑 COUPLE'S GOALS | Personal Goal Planner
B2: Set ambitious goals. Track relentlessly. Celebrate every win.
C3: Total Goals | D3: Completed | E3: In Progress | F3: Completion Rate
C4: =COUNTA(C5:C54) -> 8 | D4: =COUNTIF(H5:H54,"Completed") -> 0 | E4: =COUNTIF(H5:H54,"In Progress") -> 0 | F4: =IFERROR(COUNTIF(H5:H54,"Completed")/COUNTA(H5:H54),0) -> 0
B5: 📋 GOAL LIST — COUPLE | Add, update, and track your goals below
B6: # | C6: Goal Title | D6: Category | E6: Target Date | F6: Progress % | G6: Measure / KPI | H6: Priority | I6: Status | J6: Notes
B7: 1 | C7: Buy our first home together | D7: Finance | E7: Dec 2025 | F7: 0.35 | G7: House purchased & keys | H7: High | I7: In Progress
B8: 2 | C8: Travel to 3 new countries | D8: Travel | E8: Dec 2026 | F8: 0.33 | G8: Countries visited together | H8: High | I8: In Progress
B9: 3 | C9: Monthly date nights (12 total) | D9: Relationship | E9: Dec 2025 | F9: 0.75 | G9: Date nights completed | H9: Medium | I9: In Progress
B10: 4 | C10: Run a 5K together | D10: Health | E10: Jun 2025 | F10: 0.6 | G10: Race completed together | H10: Medium | I10: In Progress
B11: 5 | C11: Build joint investment portfolio | D11: Finance | E11: Ongoing | F11: 0.3 | G11: Portfolio value milestone | H11: High | I11: In Progress
B12: 6 | C12: Attend couples workshop / retreat | D12: Relationship | E12: Dec 2025 | F12: 0 | G12: Workshop attended | H12: Medium | I12: Not Started
B13: 7 | C13: Cook a new recipe every 2 weeks | D13: Hobbies | E13: Ongoing | F13: 0.6 | G13: Recipes cooked together | H13: Low | I13: In Progress
B14: 8
B15: 9
B16: 10
B17: 11
B18: 12
B19: 13
B20: 14
B21: 15
B22: 16
B23: 17
B24: 18
B25: 19
... B56: 50
B58: 💡 Tip: Review and update progress weekly. Use the Status dropdown to mark goals Completed, then log them in the 🏆 Achieved tab!

Sheet 🏆 Achieved
B1: 🏆 HALL OF FAME — ACHIEVED GOALS
B2: Every goal completed here is a victory. You both crushed it! 🎉
C3: 🏆 Total Wins | D3: 👨 His Wins | E3: 👩 Her Wins | F3: 💑 Joint Wins
C4: =COUNTIF(D7:D200,"Achieved") -> 0 | D4: =COUNTIFS(C7:C200,"Him",D7:D200,"Achieved") -> 0 | E4: =COUNTIFS(C7:C200,"Her",D7:D200,"Achieved") -> 0 | F4: =COUNTIFS(C7:C200,"Couple",D7:D200,"Achieved") -> 0
B5: 🎯 ACHIEVED GOALS LOG
B6: # | C6: Goal Achieved | D6: Owner | E6: Status | F6: Category | G6: Date Achieved | H6: Celebration / Note
B7: 1 | C7: Paid off credit card debt | D7: Him | E7: Achieved | F7: Finance | G7: Mar 2025 | H7: 🎉 Dinner date to celebrate!
B8: 2 | C8: Completed 30-day fitness challenge | D8: Her | E8: Achieved | F8: Health | G8: Feb 2025 | H8: 🥂 Spa day treat!
B9: 3 | C9: First holiday abroad together | D9: Couple | E9: Achieved | F9: Travel | G9: Jan 2025 | H9: ❤️ Portugal was magical!
B10: 4 | C10: Got driving licence | D10: Her | E10: Achieved | F10: Personal Growth | G10: Apr 2025 | H10: 🚗 Road trip time!
B102: 📌 How to use: When you complete a goal, copy the goal name here, set Status = Achieved, and add your celebration note! 🎊

Sheet 📅 Monthly Check-In
B1: 📅 MONTHLY COUPLE CHECK-IN
B2: Set aside 30 minutes each month to review progress together. Connection + accountability = results.
B4: 📋 MONTHLY REVIEW TEMPLATE
B5: Month | C5: His Goals Progress | D5: Her Goals Progress | E5: Couple Goals Progress | F5: Win of the Month 🏆 | G5: Challenge to Overcome | H5: Action for Next Month
B6: Jan
B7: Feb
B8: Mar
B9: Apr
B10: May
B11: Jun
B12: Jul
B13: Aug
B14: Sep
B15: Oct
B16: Nov
B17: Dec
B20: 💬 QUARTERLY REFLECTION PROMPTS
B21: Quarter | C21: Prompt 1 | D21: Answer | E21: Prompt 2 | F21: Answer | G21: Prompt 3
B22: Q1 (Mar) | C22: What goals did we make the most progress on? | E22: What slowed us down? | G22: How did we support each other?
B23: Q2 (Jun) | C23: What habits are working? | E23: What needs to change? | G23: What are we most proud of?
B24: Q3 (Sep) | C24: Are our goals still aligned with our vision? | E24: What new goals should we add? | G24: What should we drop or pause?
B25: Q4 (Dec) | C25: What was our biggest joint achievement? | E25: What are our 3 big goals for next year? | G25: How will we celebrate our wins?
B28: 💡 Schedule your monthly check-in on the same day each month — make it a ritual! With snacks 🍿
